yml2json/__init__.py
yml2json-1.1.3.dist-info/DESCRIPTION.rst
yml2json-1.1.3.dist-info/METADATA
yml2json-1.1.3.dist-info/RECORD
yml2json-1.1.3.dist-info/WHEEL
yml2json-1.1.3.dist-info/entry_points.txt
yml2json-1.1.3.dist-info/metadata.json
yml2json-1.1.3.dist-info/top_level.txt
