Metadata-Version: 2.0
Name: yml2json
Version: 1.1.3
Summary: Converts YAML input to JSON output.
Home-page: https://github.com/skyzyx/yml2json
Author: Ryan Parman
Author-email: ryan@ryanparman.com
License: MIT
Keywords: yaml yml json
Platform: UNKNOWN
Classifier: Development Status :: 4 - Beta
Classifier: Environment :: Console
Classifier: Intended Audience :: Developers
Classifier: License :: OSI Approved :: MIT License
Classifier: Natural Language :: English
Classifier: Programming Language :: Python :: 2.7
Classifier: Topic :: Utilities
Requires-Dist: PyYAML (==3.11)
Requires-Dist: python-dateutil (==2.5.2)
